replit_bot/AsyncBot.py
replit_bot/AsyncClient.py
replit_bot/AsyncPost_ql.py
replit_bot/LICENSE
replit_bot/__init__.py
replit_bot/bot.py
replit_bot/client.py
replit_bot/colors.py
replit_bot/exceptions.py
replit_bot/html_default_templates.py
replit_bot/links.py
replit_bot/param.py
replit_bot/post_ql.py
replit_bot/queries.js
replit_bot/queries.py
replit_bot/templates/index.html
replit_bot/utils/EventEmitter.py
replit_bot/utils/JSDict.py
replit_bot/utils/_uuid.py
replit_bot/utils/lines.py
replit_bot/utils/switch.py
replit_bot-4.2.18.dist-info/LICENSE
replit_bot-4.2.18.dist-info/WHEEL
replit_bot-4.2.18.dist-info/METADATA
replit_bot-4.2.18.dist-info/RECORD
