Metadata-Version: 2.1
Name: replit-bot
Version: 4.2.18
Summary: make discord.py like bots on replit and/or do replapi-it style replit interactions
Author: bigminboss
Author-email: you@example.com
Requires-Python: >=3.7,<4.0.0
Classifier: Programming Language :: Python :: 3
Classifier: Programming Language :: Python :: 3.10
Classifier: Programming Language :: Python :: 3.7
Classifier: Programming Language :: Python :: 3.8
Classifier: Programming Language :: Python :: 3.9
Requires-Dist: Flask (>=2.2.0,<3.0.0)
Requires-Dist: pyee (>=9.0.4,<10.0.0)
Requires-Dist: replit (>=3.2.4,<4.0.0)
Requires-Dist: requests (>=2.28.1,<3.0.0)
Requires-Dist: waitress (>=2.1.2,<3.0.0)
